{
  "part_id": "p02_b",
  "world": "past",
  "nodes": {
    "p02_b_node_000": {
      "id": "p02_b_node_000",
      "text_ar": "في جناح الإمبراطور، وجدته محاصراً ولا يدرك حجم المؤامرة. أقنعته بالخطر بمساعدة الوثائق التي جمعتها.",
      "reward_xp": 30,
      "choices": [
        {
          "text_ar": "استغل البيئة المحيطة لصالحك وقم بنصب فخ.",
          "next_node": "p02_b_node_001",
          "skill_check": "crafting",
          "difficulty": 16,
          "fail_next_node": "p02_b_node_000"
        },
        {
          "text_ar": "استخدم دهاءك للبحث عن حل بديل وخفي.",
          "next_node": "p02_b_node_002",
          "skill_check": "agility",
          "difficulty": 16
        }
      ]
    },
    "p02_b_node_001": {
      "id": "p02_b_node_001",
      "text_ar": "الخائن كشف عن نفسه وبدأ الهجوم على القصر بقواته والنقابة السري.",
      "reward_xp": 30,
      "choices": [
        {
          "text_ar": "اندفع بقوة وواجه التحدي مباشرة.",
          "next_node": "p02_b_node_002",
          "skill_check": "charisma",
          "difficulty": 14
        },
        {
          "text_ar": "تفاوض أو ابحث عن حلفاء في هذه اللحظة الحرجة.",
          "next_node": "p02_b_node_003",
          "skill_check": "intellect",
          "difficulty": 13
        }
      ]
    },
    "p02_b_node_002": {
      "id": "p02_b_node_002",
      "text_ar": "قمت بحماية الإمبراطور وأرشدته إلى ممر سري يؤدي إلى قلعة الحرس الملكي.",
      "reward_xp": 45,
      "choices": [
        {
          "text_ar": "حاول استخدام سحرك أو معرفتك التقنية لحل المعضلة.",
          "next_node": "p02_b_node_003",
          "skill_check": "crafting",
          "difficulty": 14
        },
        {
          "text_ar": "توقف لحظة للتفكير وتحليل الموقف قبل التصرف.",
          "next_node": "p02_b_node_004",
          "skill_check": "intellect",
          "difficulty": 17,
          "fail_next_node": "p02_b_node_002"
        },
        {
          "text_ar": "اندفع بقوة وواجه التحدي مباشرة.",
          "next_node": "p02_b_node_003",
          "skill_check": "charisma",
          "difficulty": 15
        },
        {
          "text_ar": "استخدم بصيرتك (القائد) لفتح مسار خفي لا يراه الآخرون.",
          "next_node": "p02_b_node_003",
          "required_archetype": "القائد"
        }
      ]
    },
    "p02_b_node_003": {
      "id": "p02_b_node_003",
      "text_ar": "في الطريق، واجهت زعيم نقابة 'العقرب الأسود' وجهاً لوجه.",
      "reward_xp": 49,
      "choices": [
        {
          "text_ar": "حاول استخدام سحرك أو معرفتك التقنية لحل المعضلة.",
          "next_node": "p02_b_node_004",
          "skill_check": "charisma",
          "difficulty": 19
        },
        {
          "text_ar": "اندفع بقوة وواجه التحدي مباشرة.",
          "next_node": "p02_b_node_004",
          "skill_check": "strength",
          "difficulty": 17,
          "fail_next_node": "p02_b_node_003"
        },
        {
          "text_ar": "استخدم دهاءك للبحث عن حل بديل وخفي.",
          "next_node": "p02_b_node_004",
          "skill_check": "intellect",
          "difficulty": 15
        },
        {
          "text_ar": "استخدم بصيرتك (القائد) لفتح مسار خفي لا يراه الآخرون.",
          "next_node": "p02_b_node_004",
          "required_archetype": "القائد"
        }
      ]
    },
    "p02_b_node_004": {
      "id": "p02_b_node_004",
      "text_ar": "بعد معركة ملحمية، هزمته وصادرت سلاحه السحري القديم.",
      "reward_xp": 30,
      "next_part_id": "p03_a",
      "choices": [
        {
          "text_ar": "تفاوض أو ابحث عن حلفاء في هذه اللحظة الحرجة.",
          "next_node": "p03_a_node_000",
          "skill_check": "magic",
          "difficulty": 16
        },
        {
          "text_ar": "توقف لحظة للتفكير وتحليل الموقف قبل التصرف.",
          "next_node": "p03_a_node_000",
          "skill_check": "intellect",
          "difficulty": 15
        },
        {
          "text_ar": "اعتمد على رشاقتك وسرعتك لتفادي الخطر المباشر.",
          "next_node": "p03_a_node_000",
          "skill_check": "agility",
          "difficulty": 18
        }
      ]
    }
  },
  "next_part_id": "p03_a"
}