{
  "quests": [
    {
      "id": "daily_quest_001",
      "title_ar": "الواجب اليومي 1: اجمع الوحوش الكامنة في الغابة السوداء",
      "desc_ar": "لقد طلب منك عمدة المدينة أن تقوم بهذه المهمة الحيوية اليوم. انطلق إلى الغابة السوداء وقم بـ اجمع الوحوش الكامنة. المدينة تعتمد عليك أيها البطل.",
      "stages": [
        {
          "stage_ar": "قم بالتحضير للذهاب إلى الغابة السوداء.",
          "xp": 16
        },
        {
          "stage_ar": "واجه الصعوبات أثناء محاولتك لـ اجمع الوحوش الكامنة.",
          "xp": 44
        },
        {
          "stage_ar": "عُد إلى العمدة لتقديم تقريرك.",
          "xp": 89
        }
      ],
      "reward_gold": 100
    },
    {
      "id": "daily_quest_002",
      "title_ar": "الواجب اليومي 2: دافع عن الآثار القديمة في قبو القلعة",
      "desc_ar": "لقد طلب منك عمدة المدينة أن تقوم بهذه المهمة الحيوية اليوم. انطلق إلى قبو القلعة وقم بـ دافع عن الآثار القديمة. المدينة تعتمد عليك أيها البطل.",
      "stages": [
        {
          "stage_ar": "قم بالتحضير للذهاب إلى قبو القلعة.",
          "xp": 23
        },
        {
          "stage_ar": "واجه الصعوبات أثناء محاولتك لـ دافع عن الآثار القديمة.",
          "xp": 36
        },
        {
          "stage_ar": "عُد إلى العمدة لتقديم تقريرك.",
          "xp": 48
        }
      ],
      "reward_gold": 100
    },
    {
      "id": "daily_quest_003",
      "title_ar": "الواجب اليومي 3: طهر منطقة اللصوص في الميناء القديم",
      "desc_ar": "لقد طلب منك عمدة المدينة أن تقوم بهذه المهمة الحيوية اليوم. انطلق إلى الميناء القديم وقم بـ طهر منطقة اللصوص. المدينة تعتمد عليك أيها البطل.",
      "stages": [
        {
          "stage_ar": "قم بالتحضير للذهاب إلى الميناء القديم.",
          "xp": 24
        },
        {
          "stage_ar": "واجه الصعوبات أثناء محاولتك لـ طهر منطقة اللصوص.",
          "xp": 41
        },
        {
          "stage_ar": "عُد إلى العمدة لتقديم تقريرك.",
          "xp": 99
        }
      ],
      "reward_gold": 100
    },
    {
      "id": "daily_quest_004",
      "title_ar": "الواجب اليومي 4: اكتشف سر اللصوص في سوق المدينة",
      "desc_ar": "لقد طلب منك عمدة المدينة أن تقوم بهذه المهمة الحيوية اليوم. انطلق إلى سوق المدينة وقم بـ اكتشف سر اللصوص. المدينة تعتمد عليك أيها البطل.",
      "stages": [
        {
          "stage_ar": "قم بالتحضير للذهاب إلى سوق المدينة.",
          "xp": 26
        },
        {
          "stage_ar": "واجه الصعوبات أثناء محاولتك لـ اكتشف سر اللصوص.",
          "xp": 54
        },
        {
          "stage_ar": "عُد إلى العمدة لتقديم تقريرك.",
          "xp": 42
        }
      ],
      "reward_gold": 100
    },
    {
      "id": "daily_quest_005",
      "title_ar": "الواجب اليومي 5: دافع عن اللصوص في الميناء القديم",
      "desc_ar": "لقد طلب منك عمدة المدينة أن تقوم بهذه المهمة الحيوية اليوم. انطلق إلى الميناء القديم وقم بـ دافع عن اللصوص. المدينة تعتمد عليك أيها البطل.",
      "stages": [
        {
          "stage_ar": "قم بالتحضير للذهاب إلى الميناء القديم.",
          "xp": 13
        },
        {
          "stage_ar": "واجه الصعوبات أثناء محاولتك لـ دافع عن اللصوص.",
          "xp": 57
        },
        {
          "stage_ar": "عُد إلى العمدة لتقديم تقريرك.",
          "xp": 58
        }
      ],
      "reward_gold": 100
    },
    {
      "id": "daily_quest_006",
      "title_ar": "الواجب اليومي 6: طهر منطقة حراس العهد في الغابة السوداء",
      "desc_ar": "لقد طلب منك عمدة المدينة أن تقوم بهذه المهمة الحيوية اليوم. انطلق إلى الغابة السوداء وقم بـ طهر منطقة حراس العهد. المدينة تعتمد عليك أيها البطل.",
      "stages": [
        {
          "stage_ar": "قم بالتحضير للذهاب إلى الغابة السوداء.",
          "xp": 17
        },
        {
          "stage_ar": "واجه الصعوبات أثناء محاولتك لـ طهر منطقة حراس العهد.",
          "xp": 34
        },
        {
          "stage_ar": "عُد إلى العمدة لتقديم تقريرك.",
          "xp": 65
        }
      ],
      "reward_gold": 100
    },
    {
      "id": "daily_quest_007",
      "title_ar": "الواجب اليومي 7: ابحث عن اللصوص في الميناء القديم",
      "desc_ar": "لقد طلب منك عمدة المدينة أن تقوم بهذه المهمة الحيوية اليوم. انطلق إلى الميناء القديم وقم بـ ابحث عن اللصوص. المدينة تعتمد عليك أيها البطل.",
      "stages": [
        {
          "stage_ar": "قم بالتحضير للذهاب إلى الميناء القديم.",
          "xp": 30
        },
        {
          "stage_ar": "واجه الصعوبات أثناء محاولتك لـ ابحث عن اللصوص.",
          "xp": 48
        },
        {
          "stage_ar": "عُد إلى العمدة لتقديم تقريرك.",
          "xp": 84
        }
      ],
      "reward_gold": 100
    },
    {
      "id": "daily_quest_008",
      "title_ar": "الواجب اليومي 8: ابحث عن الموارد النادرة في الغابة السوداء",
      "desc_ar": "لقد طلب منك عمدة المدينة أن تقوم بهذه المهمة الحيوية اليوم. انطلق إلى الغابة السوداء وقم بـ ابحث عن الموارد النادرة. المدينة تعتمد عليك أيها البطل.",
      "stages": [
        {
          "stage_ar": "قم بالتحضير للذهاب إلى الغابة السوداء.",
          "xp": 29
        },
        {
          "stage_ar": "واجه الصعوبات أثناء محاولتك لـ ابحث عن الموارد النادرة.",
          "xp": 40
        },
        {
          "stage_ar": "عُد إلى العمدة لتقديم تقريرك.",
          "xp": 99
        }
      ],
      "reward_gold": 100
    },
    {
      "id": "daily_quest_009",
      "title_ar": "الواجب اليومي 9: ابحث عن الآثار القديمة في سوق المدينة",
      "desc_ar": "لقد طلب منك عمدة المدينة أن تقوم بهذه المهمة الحيوية اليوم. انطلق إلى سوق المدينة وقم بـ ابحث عن الآثار القديمة. المدينة تعتمد عليك أيها البطل.",
      "stages": [
        {
          "stage_ar": "قم بالتحضير للذهاب إلى سوق المدينة.",
          "xp": 25
        },
        {
          "stage_ar": "واجه الصعوبات أثناء محاولتك لـ ابحث عن الآثار القديمة.",
          "xp": 47
        },
        {
          "stage_ar": "عُد إلى العمدة لتقديم تقريرك.",
          "xp": 82
        }
      ],
      "reward_gold": 100
    },
    {
      "id": "daily_quest_010",
      "title_ar": "الواجب اليومي 10: تحدث إلى نقابة الظلال في المعبد المنسي",
      "desc_ar": "لقد طلب منك عمدة المدينة أن تقوم بهذه المهمة الحيوية اليوم. انطلق إلى المعبد المنسي وقم بـ تحدث إلى نقابة الظلال. المدينة تعتمد عليك أيها البطل.",
      "stages": [
        {
          "stage_ar": "قم بالتحضير للذهاب إلى المعبد المنسي.",
          "xp": 16
        },
        {
          "stage_ar": "واجه الصعوبات أثناء محاولتك لـ تحدث إلى نقابة الظلال.",
          "xp": 60
        },
        {
          "stage_ar": "عُد إلى العمدة لتقديم تقريرك.",
          "xp": 49
        }
      ],
      "reward_gold": 100
    },
    {
      "id": "daily_quest_011",
      "title_ar": "الواجب اليومي 11: دافع عن الموارد النادرة في الغابة السوداء",
      "desc_ar": "لقد طلب منك عمدة المدينة أن تقوم بهذه المهمة الحيوية اليوم. انطلق إلى الغابة السوداء وقم بـ دافع عن الموارد النادرة. المدينة تعتمد عليك أيها البطل.",
      "stages": [
        {
          "stage_ar": "قم بالتحضير للذهاب إلى الغابة السوداء.",
          "xp": 30
        },
        {
          "stage_ar": "واجه الصعوبات أثناء محاولتك لـ دافع عن الموارد النادرة.",
          "xp": 39
        },
        {
          "stage_ar": "عُد إلى العمدة لتقديم تقريرك.",
          "xp": 64
        }
      ],
      "reward_gold": 100
    },
    {
      "id": "daily_quest_012",
      "title_ar": "الواجب اليومي 12: اكتشف سر نقابة الظلال في المعبد المنسي",
      "desc_ar": "لقد طلب منك عمدة المدينة أن تقوم بهذه المهمة الحيوية اليوم. انطلق إلى المعبد المنسي وقم بـ اكتشف سر نقابة الظلال. المدينة تعتمد عليك أيها البطل.",
      "stages": [
        {
          "stage_ar": "قم بالتحضير للذهاب إلى المعبد المنسي.",
          "xp": 15
        },
        {
          "stage_ar": "واجه الصعوبات أثناء محاولتك لـ اكتشف سر نقابة الظلال.",
          "xp": 53
        },
        {
          "stage_ar": "عُد إلى العمدة لتقديم تقريرك.",
          "xp": 62
        }
      ],
      "reward_gold": 100
    },
    {
      "id": "daily_quest_013",
      "title_ar": "الواجب اليومي 13: ابحث عن حراس العهد في الميناء القديم",
      "desc_ar": "لقد طلب منك عمدة المدينة أن تقوم بهذه المهمة الحيوية اليوم. انطلق إلى الميناء القديم وقم بـ ابحث عن حراس العهد. المدينة تعتمد عليك أيها البطل.",
      "stages": [
        {
          "stage_ar": "قم بالتحضير للذهاب إلى الميناء القديم.",
          "xp": 23
        },
        {
          "stage_ar": "واجه الصعوبات أثناء محاولتك لـ ابحث عن حراس العهد.",
          "xp": 49
        },
        {
          "stage_ar": "عُد إلى العمدة لتقديم تقريرك.",
          "xp": 85
        }
      ],
      "reward_gold": 100
    },
    {
      "id": "daily_quest_014",
      "title_ar": "الواجب اليومي 14: تحدث إلى الموارد النادرة في سوق المدينة",
      "desc_ar": "لقد طلب منك عمدة المدينة أن تقوم بهذه المهمة الحيوية اليوم. انطلق إلى سوق المدينة وقم بـ تحدث إلى الموارد النادرة. المدينة تعتمد عليك أيها البطل.",
      "stages": [
        {
          "stage_ar": "قم بالتحضير للذهاب إلى سوق المدينة.",
          "xp": 25
        },
        {
          "stage_ar": "واجه الصعوبات أثناء محاولتك لـ تحدث إلى الموارد النادرة.",
          "xp": 57
        },
        {
          "stage_ar": "عُد إلى العمدة لتقديم تقريرك.",
          "xp": 45
        }
      ],
      "reward_gold": 100
    },
    {
      "id": "daily_quest_015",
      "title_ar": "الواجب اليومي 15: ابحث عن الوحوش الكامنة في سوق المدينة",
      "desc_ar": "لقد طلب منك عمدة المدينة أن تقوم بهذه المهمة الحيوية اليوم. انطلق إلى سوق المدينة وقم بـ ابحث عن الوحوش الكامنة. المدينة تعتمد عليك أيها البطل.",
      "stages": [
        {
          "stage_ar": "قم بالتحضير للذهاب إلى سوق المدينة.",
          "xp": 19
        },
        {
          "stage_ar": "واجه الصعوبات أثناء محاولتك لـ ابحث عن الوحوش الكامنة.",
          "xp": 50
        },
        {
          "stage_ar": "عُد إلى العمدة لتقديم تقريرك.",
          "xp": 56
        }
      ],
      "reward_gold": 100
    },
    {
      "id": "daily_quest_016",
      "title_ar": "الواجب اليومي 16: طهر منطقة الآثار القديمة في الميناء القديم",
      "desc_ar": "لقد طلب منك عمدة المدينة أن تقوم بهذه المهمة الحيوية اليوم. انطلق إلى الميناء القديم وقم بـ طهر منطقة الآثار القديمة. المدينة تعتمد عليك أيها البطل.",
      "stages": [
        {
          "stage_ar": "قم بالتحضير للذهاب إلى الميناء القديم.",
          "xp": 26
        },
        {
          "stage_ar": "واجه الصعوبات أثناء محاولتك لـ طهر منطقة الآثار القديمة.",
          "xp": 51
        },
        {
          "stage_ar": "عُد إلى العمدة لتقديم تقريرك.",
          "xp": 71
        }
      ],
      "reward_gold": 100
    },
    {
      "id": "daily_quest_017",
      "title_ar": "الواجب اليومي 17: اكتشف سر الوحوش الكامنة في الغابة السوداء",
      "desc_ar": "لقد طلب منك عمدة المدينة أن تقوم بهذه المهمة الحيوية اليوم. انطلق إلى الغابة السوداء وقم بـ اكتشف سر الوحوش الكامنة. المدينة تعتمد عليك أيها البطل.",
      "stages": [
        {
          "stage_ar": "قم بالتحضير للذهاب إلى الغابة السوداء.",
          "xp": 30
        },
        {
          "stage_ar": "واجه الصعوبات أثناء محاولتك لـ اكتشف سر الوحوش الكامنة.",
          "xp": 30
        },
        {
          "stage_ar": "عُد إلى العمدة لتقديم تقريرك.",
          "xp": 82
        }
      ],
      "reward_gold": 100
    },
    {
      "id": "daily_quest_018",
      "title_ar": "الواجب اليومي 18: ابحث عن الوحوش الكامنة في الميناء القديم",
      "desc_ar": "لقد طلب منك عمدة المدينة أن تقوم بهذه المهمة الحيوية اليوم. انطلق إلى الميناء القديم وقم بـ ابحث عن الوحوش الكامنة. المدينة تعتمد عليك أيها البطل.",
      "stages": [
        {
          "stage_ar": "قم بالتحضير للذهاب إلى الميناء القديم.",
          "xp": 10
        },
        {
          "stage_ar": "واجه الصعوبات أثناء محاولتك لـ ابحث عن الوحوش الكامنة.",
          "xp": 49
        },
        {
          "stage_ar": "عُد إلى العمدة لتقديم تقريرك.",
          "xp": 71
        }
      ],
      "reward_gold": 100
    },
    {
      "id": "daily_quest_019",
      "title_ar": "الواجب اليومي 19: اجمع الوحوش الكامنة في الميناء القديم",
      "desc_ar": "لقد طلب منك عمدة المدينة أن تقوم بهذه المهمة الحيوية اليوم. انطلق إلى الميناء القديم وقم بـ اجمع الوحوش الكامنة. المدينة تعتمد عليك أيها البطل.",
      "stages": [
        {
          "stage_ar": "قم بالتحضير للذهاب إلى الميناء القديم.",
          "xp": 25
        },
        {
          "stage_ar": "واجه الصعوبات أثناء محاولتك لـ اجمع الوحوش الكامنة.",
          "xp": 48
        },
        {
          "stage_ar": "عُد إلى العمدة لتقديم تقريرك.",
          "xp": 100
        }
      ],
      "reward_gold": 100
    },
    {
      "id": "daily_quest_020",
      "title_ar": "الواجب اليومي 20: دافع عن نقابة الظلال في الميناء القديم",
      "desc_ar": "لقد طلب منك عمدة المدينة أن تقوم بهذه المهمة الحيوية اليوم. انطلق إلى الميناء القديم وقم بـ دافع عن نقابة الظلال. المدينة تعتمد عليك أيها البطل.",
      "stages": [
        {
          "stage_ar": "قم بالتحضير للذهاب إلى الميناء القديم.",
          "xp": 17
        },
        {
          "stage_ar": "واجه الصعوبات أثناء محاولتك لـ دافع عن نقابة الظلال.",
          "xp": 50
        },
        {
          "stage_ar": "عُد إلى العمدة لتقديم تقريرك.",
          "xp": 61
        }
      ],
      "reward_gold": 100
    }
  ]
}