{
  "part_id": "p01_a",
  "world": "alternate",
  "nodes": {
    "p01_a_node_000": {
      "id": "p01_a_node_000",
      "text_ar": "في قلعة الزمن المتوقفة، حيث تتدلى الساعات من السقف بلا حركة، تكتشف آلة غامضة قد تكون مفتاحاً لعودتك إلى عالمك.\n\nتكتشف أن الآلة الغامضة تتطلب طاقة حيوية لتشغيلها، وتدرك أنك قد تضطر إلى التضحية بجزء من نفسك.",
      "reward_xp": 36,
      "choices": [
        {
          "text_ar": "حاول فهم النسخة الأخرى منك واستخلاص المعرفة منها.",
          "next_node": "p01_a_node_001",
          "skill_check": "strength",
          "difficulty": 12
        },
        {
          "text_ar": "استخدم الكريستال المتوهج للانتقال إلى واقع آخر.",
          "next_node": "p01_a_node_001",
          "skill_check": "magic",
          "difficulty": 17,
          "fail_next_node": "p01_a_node_000"
        },
        {
          "text_ar": "استخدم قواك العقلية للسيطرة على الصدع الزمني.",
          "next_node": "p01_a_node_001",
          "skill_check": "stealth",
          "difficulty": 14,
          "fail_next_node": "p01_a_node_000"
        }
      ]
    },
    "p01_a_node_001": {
      "id": "p01_a_node_001",
      "text_ar": "في الأراضي القاحلة التي تفصل بين الأبعاد المتعددة، حيث تتلاشى قوانين الفيزياء وتتشوه الألوان، تقف أمام صدع زمني يتوهج بطاقة غريبة.\n\nتجد قطعة من الكريستال المتوهج، وبمجرد لمسها تنتقل إلى واقع بديل يختلف تماماً عن واقعك.",
      "reward_xp": 19,
      "choices": [
        {
          "text_ar": "استخدم الكريستال المتوهج للانتقال إلى واقع آخر.",
          "next_node": "p01_a_node_002",
          "skill_check": "magic",
          "difficulty": 10
        },
        {
          "text_ar": "استخدم الكريستال المتوهج للانتقال إلى واقع آخر.",
          "next_node": "p01_a_node_002",
          "skill_check": "crafting",
          "difficulty": 13,
          "fail_next_node": "p01_a_node_001"
        },
        {
          "text_ar": "شغل الآلة الغامضة باستخدام طاقتك الحيوية.",
          "next_node": "p01_a_node_002",
          "skill_check": "strength",
          "difficulty": 14
        },
        {
          "text_ar": "استخدم حدسك (الخارج عن القانون) لاكتشاف ممر خفي.",
          "next_node": "p01_a_node_002",
          "required_archetype": "الخارج عن القانون"
        }
      ]
    },
    "p01_a_node_002": {
      "id": "p01_a_node_002",
      "text_ar": "على حافة الهاوية التي تطل على فراغ لا نهائي، تشعر بقوة سحب هائلة تحاول ابتلاعك.\n\nتسمع صوتاً يهمس لك بأسرار الكون، وتدرك أن عقلك قد لا يتحمل كل هذه المعرفة.",
      "reward_xp": 21,
      "choices": [
        {
          "text_ar": "شغل الآلة الغامضة باستخدام طاقتك الحيوية.",
          "next_node": "p01_a_node_003",
          "skill_check": "stealth",
          "difficulty": 20
        },
        {
          "text_ar": "استخدم الكريستال المتوهج للانتقال إلى واقع آخر.",
          "next_node": "p01_a_node_003",
          "skill_check": "charisma",
          "difficulty": 17,
          "fail_next_node": "p01_a_node_002"
        },
        {
          "text_ar": "حاول فهم النسخة الأخرى منك واستخلاص المعرفة منها.",
          "next_node": "p01_a_node_003",
          "skill_check": "intellect",
          "difficulty": 20,
          "fail_next_node": "p01_a_node_002"
        }
      ]
    },
    "p01_a_node_003": {
      "id": "p01_a_node_003",
      "text_ar": "في قلعة الزمن المتوقفة، حيث تتدلى الساعات من السقف بلا حركة، تكتشف آلة غامضة قد تكون مفتاحاً لعودتك إلى عالمك.\n\nتكتشف أن الآلة الغامضة تتطلب طاقة حيوية لتشغيلها، وتدرك أنك قد تضطر إلى التضحية بجزء من نفسك.",
      "reward_xp": 10,
      "choices": [
        {
          "text_ar": "استخدم قواك العقلية للسيطرة على الصدع الزمني.",
          "next_node": "p01_a_node_004",
          "skill_check": "charisma",
          "difficulty": 15
        },
        {
          "text_ar": "استخدم الكريستال المتوهج للانتقال إلى واقع آخر.",
          "next_node": "p01_a_node_004",
          "skill_check": "magic",
          "difficulty": 17
        },
        {
          "text_ar": "حاول فهم النسخة الأخرى منك واستخلاص المعرفة منها.",
          "next_node": "p01_a_node_004",
          "skill_check": "intellect",
          "difficulty": 10
        }
      ]
    },
    "p01_a_node_004": {
      "id": "p01_a_node_004",
      "text_ar": "داخل المتاهة البلورية التي تغير شكلها باستمرار، تجد نفسك محاصراً بين انعكاسات متعددة لشخصيتك.\n\nتكتشف أن الآلة الغامضة تتطلب طاقة حيوية لتشغيلها، وتدرك أنك قد تضطر إلى التضحية بجزء من نفسك.",
      "reward_xp": 40,
      "choices": [
        {
          "text_ar": "شغل الآلة الغامضة باستخدام طاقتك الحيوية.",
          "next_node": "p01_a_node_005",
          "skill_check": "charisma",
          "difficulty": 17
        },
        {
          "text_ar": "استخدم الكريستال المتوهج للانتقال إلى واقع آخر.",
          "next_node": "p01_a_node_005",
          "skill_check": "agility",
          "difficulty": 17
        },
        {
          "text_ar": "شغل الآلة الغامضة باستخدام طاقتك الحيوية.",
          "next_node": "p01_a_node_005",
          "skill_check": "crafting",
          "difficulty": 11
        }
      ]
    },
    "p01_a_node_005": {
      "id": "p01_a_node_005",
      "text_ar": "على حافة الهاوية التي تطل على فراغ لا نهائي، تشعر بقوة سحب هائلة تحاول ابتلاعك.\n\nتكتشف أن الآلة الغامضة تتطلب طاقة حيوية لتشغيلها، وتدرك أنك قد تضطر إلى التضحية بجزء من نفسك.",
      "reward_xp": 12,
      "choices": [
        {
          "text_ar": "استخدم قواك العقلية للسيطرة على الصدع الزمني.",
          "next_node": "p01_a_node_006",
          "skill_check": "stealth",
          "difficulty": 19
        },
        {
          "text_ar": "استخدم قواك العقلية للسيطرة على الصدع الزمني.",
          "next_node": "p01_a_node_006",
          "skill_check": "magic",
          "difficulty": 17,
          "fail_next_node": "p01_a_node_005"
        },
        {
          "text_ar": "حاول فهم النسخة الأخرى منك واستخلاص المعرفة منها.",
          "next_node": "p01_a_node_006",
          "skill_check": "agility",
          "difficulty": 13
        }
      ]
    },
    "p01_a_node_006": {
      "id": "p01_a_node_006",
      "text_ar": "على حافة الهاوية التي تطل على فراغ لا نهائي، تشعر بقوة سحب هائلة تحاول ابتلاعك.\n\nتسمع صوتاً يهمس لك بأسرار الكون، وتدرك أن عقلك قد لا يتحمل كل هذه المعرفة.",
      "reward_xp": 26,
      "choices": [
        {
          "text_ar": "استخدم الكريستال المتوهج للانتقال إلى واقع آخر.",
          "next_node": "p01_a_node_007",
          "skill_check": "intellect",
          "difficulty": 19,
          "fail_next_node": "p01_a_node_006"
        },
        {
          "text_ar": "شغل الآلة الغامضة باستخدام طاقتك الحيوية.",
          "next_node": "p01_a_node_007",
          "skill_check": "agility",
          "difficulty": 15
        },
        {
          "text_ar": "شغل الآلة الغامضة باستخدام طاقتك الحيوية.",
          "next_node": "p01_a_node_007",
          "skill_check": "charisma",
          "difficulty": 20
        },
        {
          "text_ar": "استخدم حدسك (العالم) لاكتشاف ممر خفي.",
          "next_node": "p01_a_node_007",
          "required_archetype": "العالم"
        }
      ]
    },
    "p01_a_node_007": {
      "id": "p01_a_node_007",
      "text_ar": "في قلعة الزمن المتوقفة، حيث تتدلى الساعات من السقف بلا حركة، تكتشف آلة غامضة قد تكون مفتاحاً لعودتك إلى عالمك.\n\nتجد قطعة من الكريستال المتوهج، وبمجرد لمسها تنتقل إلى واقع بديل يختلف تماماً عن واقعك.",
      "reward_xp": 47,
      "choices": [
        {
          "text_ar": "شغل الآلة الغامضة باستخدام طاقتك الحيوية.",
          "next_node": "p01_a_node_008",
          "skill_check": "crafting",
          "difficulty": 13
        },
        {
          "text_ar": "شغل الآلة الغامضة باستخدام طاقتك الحيوية.",
          "next_node": "p01_a_node_008",
          "skill_check": "magic",
          "difficulty": 13
        },
        {
          "text_ar": "استخدم حدسك (الحارس) لاكتشاف ممر خفي.",
          "next_node": "p01_a_node_008",
          "required_archetype": "الحارس"
        }
      ]
    },
    "p01_a_node_008": {
      "id": "p01_a_node_008",
      "text_ar": "على حافة الهاوية التي تطل على فراغ لا نهائي، تشعر بقوة سحب هائلة تحاول ابتلاعك.\n\nتلتقي بنسخة أخرى منك تحمل ذكريات ومشاعر مختلفة، وتحاول إقناعك بتغيير مسارك.",
      "reward_xp": 43,
      "choices": [
        {
          "text_ar": "استخدم قواك العقلية للسيطرة على الصدع الزمني.",
          "next_node": "p01_a_node_009",
          "skill_check": "strength",
          "difficulty": 17
        },
        {
          "text_ar": "استخدم قواك العقلية للسيطرة على الصدع الزمني.",
          "next_node": "p01_a_node_009",
          "skill_check": "magic",
          "difficulty": 11
        },
        {
          "text_ar": "استخدم قواك العقلية للسيطرة على الصدع الزمني.",
          "next_node": "p01_a_node_009",
          "skill_check": "charisma",
          "difficulty": 20
        }
      ]
    },
    "p01_a_node_009": {
      "id": "p01_a_node_009",
      "text_ar": "داخل المتاهة البلورية التي تغير شكلها باستمرار، تجد نفسك محاصراً بين انعكاسات متعددة لشخصيتك.\n\nتلتقي بنسخة أخرى منك تحمل ذكريات ومشاعر مختلفة، وتحاول إقناعك بتغيير مسارك.",
      "reward_xp": 34,
      "next_part_id": "p01_b",
      "choices": [
        {
          "text_ar": "حاول فهم النسخة الأخرى منك واستخلاص المعرفة منها.",
          "next_node": "p01_b_node_000",
          "skill_check": "crafting",
          "difficulty": 10
        },
        {
          "text_ar": "شغل الآلة الغامضة باستخدام طاقتك الحيوية.",
          "next_node": "p01_b_node_000",
          "skill_check": "strength",
          "difficulty": 11
        },
        {
          "text_ar": "حاول فهم النسخة الأخرى منك واستخلاص المعرفة منها.",
          "next_node": "p01_b_node_000",
          "skill_check": "intellect",
          "difficulty": 18
        }
      ]
    }
  },
  "next_part_id": "p01_b"
}